{"cameraMode":{"drawMode":0,"name":"Shaded","section":"Shading Mode"},"sceneLighting":true,"audioPlay":false,"sceneViewState":{"m_AlwaysRefresh":false,"showFog":true,"showSkybox":true,"showFlares":true,"showImageEffects":true,"showParticleSystems":true,"showVisualEffectGraphs":true,"m_FxEnabled":true},"in2DMode":false,"pivot":{"x":13.963391304016114,"y":-2.1745595932006838,"z":-1.7362743616104127},"rotation":{"x":-0.22774356603622437,"y":0.662971019744873,"z":-0.22287806868553163,"w":-0.6774500608444214},"size":6.721395969390869,"orthographic":false}